vtspy/__init__.py
vtspy/config.py
vtspy/download.py
vtspy/model.py
vtspy/plotting.py
vtspy/utils.py
vtspy/version.py
vtspy/analysis/__init__.py
vtspy/analysis/fermi_analysis.py
vtspy/analysis/joint_analysis.py
vtspy/analysis/veritas_analysis.py
vtspy/external/__init__.py
vtspy/external/agnpy.py
vtspy-0.1.1.dist-info/LICENSE.txt
vtspy-0.1.1.dist-info/METADATA
vtspy-0.1.1.dist-info/WHEEL
vtspy-0.1.1.dist-info/top_level.txt
vtspy-0.1.1.dist-info/RECORD
